{"id_estacion":"1379","tipo_estacion":"Terrestre","margen_estacion":"I","horario_estacion":"L: 06:00-22:00","direccion_estacion":"AVDA. DE EXTREMADURA, S/N (EX-104 km 37,2)","latitud_estacion":38.716333,"longitud_estacion":-5.535,"ubicacion":{"id_localidad":"462","nombre_localidad":"CASTUERA","id_municipio":"330","nombre_municipio":"CASTUERA","id_provincia":"7","nombre_provincia":"BADAJOZ","id_codigo_postal":"520","numero_codigo_postal":"06420"},"empresa":{"id_empresa":"6","nombre_empresa":"CEPSA"},"combustibles":[{"id_carburante":"8","tipo_carburante":"gasóleo B","precio_carburante":1.099,"fecha_act_precio_carburante":"3/11/24 0:29"}]}