{"id_estacion":"1670","tipo_estacion":"Terrestre","margen_estacion":"D","horario_estacion":"L-D: 24H","direccion_estacion":"CALLE BAJOLI ( POLIGONO INDUSTRIAL ARTRUIX ), 39","latitud_estacion":39.883917,"longitud_estacion":4.240472,"ubicacion":{"id_localidad":"584","nombre_localidad":"MAO","id_municipio":"433","nombre_municipio":"MAHÓN","id_provincia":"8","nombre_provincia":"BALEARS (ILLES)","id_codigo_postal":"645","numero_codigo_postal":"07714"},"empresa":{"id_empresa":"26","nombre_empresa":"GMOIL"},"combustibles":[{"id_carburante":"6","tipo_carburante":"gasóleo A","precio_carburante":1.419,"fecha_act_precio_carburante":"11/11/24 10:25"}]}