{"id_estacion":"10580","tipo_estacion":"Terrestre","margen_estacion":"D","horario_estacion":"L-D: 06:00-22:00","direccion_estacion":"AUTOVIA ANTIGUA N-IV KM. 117,6","latitud_estacion":39.478611,"longitud_estacion":-3.528806,"ubicacion":{"id_localidad":"3765","nombre_localidad":"MADRIDEJOS","id_municipio":"2982","nombre_municipio":"MADRIDEJOS","id_provincia":"48","nombre_provincia":"TOLEDO","id_codigo_postal":"4163","numero_codigo_postal":"45710"},"empresa":{"id_empresa":"3552","nombre_empresa":"CEPSA . LOHANA"},"combustibles":[{"id_carburante":"7","tipo_carburante":"gasóleo Premium","precio_carburante":1.529,"fecha_act_precio_carburante":"11/11/24 0:00"}]}