{"id_estacion":"11758","tipo_estacion":"Terrestre","margen_estacion":"I","horario_estacion":"L-V: 07:00-14:00 y 16:00-19:00; S: 08:00-15:00","direccion_estacion":"CARRETERA A-1104 KM. 26,1","latitud_estacion":41.637972,"longitud_estacion":-0.419389,"ubicacion":{"id_localidad":"4201","nombre_localidad":"MONEGRILLO","id_municipio":"3378","nombre_municipio":"MONEGRILLO","id_provincia":"52","nombre_provincia":"ZARAGOZA","id_codigo_postal":"4634","numero_codigo_postal":"50164"},"empresa":{"id_empresa":"2","nombre_empresa":"REPSOL"},"combustibles":[{"id_carburante":"8","tipo_carburante":"gasóleo B","precio_carburante":1.144,"fecha_act_precio_carburante":"16/11/24 0:00"}]}