{"id_estacion":"4960","tipo_estacion":"Terrestre","margen_estacion":"I","horario_estacion":"L-D: 07:00-23:00","direccion_estacion":"CARRETERA N-II KM. 775,65","latitud_estacion":42.424917,"longitud_estacion":2.868333,"ubicacion":{"id_localidad":"1768","nombre_localidad":"LA JONQUERA","id_municipio":"1390","nombre_municipio":"JONQUERA (LA)","id_provincia":"22","nombre_provincia":"GIRONA","id_codigo_postal":"1922","numero_codigo_postal":"17700"},"empresa":{"id_empresa":"54","nombre_empresa":"BP"},"combustibles":[{"id_carburante":"7","tipo_carburante":"gasóleo Premium","precio_carburante":1.587,"fecha_act_precio_carburante":"12/11/24 23:00"}]}