{"id_estacion":"9332","tipo_estacion":"Terrestre","margen_estacion":"N","horario_estacion":"L-D: 24H","direccion_estacion":"CALLE AVENIDA DE LOS PUEBLOS, 6","latitud_estacion":28.066361,"longitud_estacion":-16.724083,"ubicacion":{"id_localidad":"3303","nombre_localidad":"PLAYA DE LAS AMERICAS (ARONA)","id_municipio":"2580","nombre_municipio":"ARONA","id_provincia":"42","nombre_provincia":"SANTA CRUZ DE TENERIFE","id_codigo_postal":"3648","numero_codigo_postal":"38660"},"empresa":{"id_empresa":"3124","nombre_empresa":"BP PLAYA LAS AMERICAS"},"combustibles":[{"id_carburante":"7","tipo_carburante":"gasóleo Premium","precio_carburante":1.349,"fecha_act_precio_carburante":"16/11/24 0:00"}]}