{"id_estacion":"5871","tipo_estacion":"Terrestre","margen_estacion":"I","horario_estacion":"L: 06:00-22:00","direccion_estacion":"CARRETERA N-323-A KM. 40,4","latitud_estacion":37.777861,"longitud_estacion":-3.733889,"ubicacion":{"id_localidad":"2156","nombre_localidad":"GUARDIA DE JAEN (LA)","id_municipio":"1740","nombre_municipio":"GUARDIA DE JAÉN (LA)","id_provincia":"27","nombre_provincia":"JAÉN","id_codigo_postal":"2337","numero_codigo_postal":"23170"},"empresa":{"id_empresa":"2","nombre_empresa":"REPSOL"},"combustibles":[{"id_carburante":"8","tipo_carburante":"gasóleo B","precio_carburante":1.249,"fecha_act_precio_carburante":"16/11/24 0:01"}]}