{"id_estacion":"3398","tipo_estacion":"Terrestre","margen_estacion":"N","horario_estacion":"L-V: 09:00-19:00","direccion_estacion":"PASEO ESTRADA","latitud_estacion":43.37032,"longitud_estacion":-4.28156,"ubicacion":{"id_localidad":"1143","nombre_localidad":"COMILLAS","id_municipio":"900","nombre_municipio":"COMILLAS","id_provincia":"14","nombre_provincia":"CANTABRIA","id_codigo_postal":"1275","numero_codigo_postal":"39520"},"empresa":{"id_empresa":"1083","nombre_empresa":"COOPERATIVA RUISEÑADA"},"combustibles":[{"id_carburante":"6","tipo_carburante":"gasóleo A","precio_carburante":1.298,"fecha_act_precio_carburante":"11/11/24 14:55"}]}