{"id_estacion":"1297","tipo_estacion":"Terrestre","margen_estacion":"N","horario_estacion":"L-D: 06:00-22:00","direccion_estacion":"CARRETERA BA089 KM. 42,700","latitud_estacion":38.792417,"longitud_estacion":-6.261611,"ubicacion":{"id_localidad":"436","nombre_localidad":"ALANGE","id_municipio":"308","nombre_municipio":"ALANGE","id_provincia":"7","nombre_provincia":"BADAJOZ","id_codigo_postal":"486","numero_codigo_postal":"06840"},"empresa":{"id_empresa":"504","nombre_empresa":"HNOS GUILLEN MONTERO S.A.L."},"combustibles":[{"id_carburante":"8","tipo_carburante":"gasóleo B","precio_carburante":1.189,"fecha_act_precio_carburante":"14/11/24 12:45"}]}