{"id_estacion":"2244","tipo_estacion":"Terrestre","margen_estacion":"I","horario_estacion":"L-D: 24H","direccion_estacion":"CARRETERA NACIONAL II KM. 532","latitud_estacion":41.61775,"longitud_estacion":1.399361,"ubicacion":{"id_localidad":"713","nombre_localidad":"MONTMANEU","id_municipio":"542","nombre_municipio":"MONTMANEU","id_provincia":"9","nombre_provincia":"BARCELONA","id_codigo_postal":"834","numero_codigo_postal":"08717"},"empresa":{"id_empresa":"778","nombre_empresa":"LA PANADELLA"},"combustibles":[{"precio_carburante":0.0}]}