{"id_estacion":"5600","tipo_estacion":"Terrestre","margen_estacion":"D","horario_estacion":"L-D: 24H","direccion_estacion":"CARRETERA A472 KM. 34,90","latitud_estacion":37.387028,"longitud_estacion":-6.399694,"ubicacion":{"id_localidad":"2023","nombre_localidad":"MANZANILLA","id_municipio":"1618","nombre_municipio":"MANZANILLA","id_provincia":"25","nombre_provincia":"HUELVA","id_codigo_postal":"2197","numero_codigo_postal":"21890"},"empresa":{"id_empresa":"1903","nombre_empresa":"AGD"},"combustibles":[{"id_carburante":"6","tipo_carburante":"gasóleo A","precio_carburante":1.268,"fecha_act_precio_carburante":"15/11/24 0:01"}]}