{"id_estacion":"4121","tipo_estacion":"Terrestre","margen_estacion":"I","horario_estacion":"L-D: 06:00-23:00","direccion_estacion":"AVENIDA DE LA INFANCIA, 15","latitud_estacion":37.414972,"longitud_estacion":-4.483083,"ubicacion":{"id_localidad":"1393","nombre_localidad":"LUCENA","id_municipio":"1108","nombre_municipio":"LUCENA","id_provincia":"18","nombre_provincia":"CÓRDOBA","id_codigo_postal":"1540","numero_codigo_postal":"14900"},"empresa":{"id_empresa":"1390","nombre_empresa":"COOPERATIVA LUCENA"},"combustibles":[{"id_carburante":"8","tipo_carburante":"gasóleo B","precio_carburante":0.919,"fecha_act_precio_carburante":"11/11/24 11:16"}]}