{"id_estacion":"6173","tipo_estacion":"Terrestre","margen_estacion":"D","horario_estacion":"L-D: 07:00-23:00","direccion_estacion":"CARRETERA LA BAÑEZA-LA MAGDALENA KM. 87,3","latitud_estacion":42.512611,"longitud_estacion":-5.890694,"ubicacion":{"id_localidad":"2269","nombre_localidad":"GAVILANES","id_municipio":"1845","nombre_municipio":"TURCIA","id_provincia":"28","nombre_provincia":"LEÓN","id_codigo_postal":"2463","numero_codigo_postal":"24285"},"empresa":{"id_empresa":"517","nombre_empresa":"GUAY"},"combustibles":[{"id_carburante":"8","tipo_carburante":"gasóleo B","precio_carburante":1.219,"fecha_act_precio_carburante":"11/11/24 21:58"}]}