{"id_estacion":"3274","tipo_estacion":"Terrestre","margen_estacion":"I","horario_estacion":"L-D: 24H","direccion_estacion":"CALLE ALBERT EINSTEIN, 17","latitud_estacion":36.6115,"longitud_estacion":-6.195361,"ubicacion":{"id_localidad":"1095","nombre_localidad":"ARENALES (LOS)","id_municipio":"873","nombre_municipio":"PUERTO DE SANTA MARÍA (EL)","id_provincia":"13","nombre_provincia":"CÁDIZ","id_codigo_postal":"1236","numero_codigo_postal":"11500"},"empresa":{"id_empresa":"121","nombre_empresa":"PETROPRIX"},"combustibles":[{"id_carburante":"6","tipo_carburante":"gasóleo A","precio_carburante":1.289,"fecha_act_precio_carburante":"15/11/24 14:32"}]}