{"id_estacion":"8375","tipo_estacion":"Terrestre","margen_estacion":"N","horario_estacion":"L-D: 24H","direccion_estacion":"CAMINO EL CEMENTERIO S/N","latitud_estacion":42.325111,"longitud_estacion":-1.743139,"ubicacion":{"id_localidad":"2883","nombre_localidad":"MARCILLA","id_municipio":"2290","nombre_municipio":"MARCILLA","id_provincia":"35","nombre_provincia":"NAVARRA","id_codigo_postal":"3178","numero_codigo_postal":"31340"},"empresa":{"id_empresa":"2769","nombre_empresa":"SDAD. COOP DEL CAMPO"},"combustibles":[{"id_carburante":"8","tipo_carburante":"gasóleo B","precio_carburante":0.95,"fecha_act_precio_carburante":"11/11/24 13:21"}]}