{"id_estacion":"4944","tipo_estacion":"Terrestre","margen_estacion":"D","horario_estacion":"L-D: 24H","direccion_estacion":"RDA. FORT ROIG, 21 (URB. MONTJUIC)","latitud_estacion":41.994472,"longitud_estacion":2.833639,"ubicacion":{"id_localidad":"1766","nombre_localidad":"GIRONA","id_municipio":"1388","nombre_municipio":"GIRONA","id_provincia":"22","nombre_provincia":"GIRONA","id_codigo_postal":"1920","numero_codigo_postal":"17007"},"empresa":{"id_empresa":"1674","nombre_empresa":"MIFASCET,SLU"},"combustibles":[{"id_carburante":"7","tipo_carburante":"gasóleo Premium","precio_carburante":1.509,"fecha_act_precio_carburante":"11/11/24 10:59"}]}