{"id_estacion":"9899","tipo_estacion":"Terrestre","margen_estacion":"I","horario_estacion":"L: 24H","direccion_estacion":"CARRETERA OSUNA-EL SAUCEJO KM. 0,200","latitud_estacion":37.231972,"longitud_estacion":-5.115278,"ubicacion":{"id_localidad":"3499","nombre_localidad":"OSUNA","id_municipio":"2736","nombre_municipio":"OSUNA","id_provincia":"44","nombre_provincia":"SEVILLA","id_codigo_postal":"3873","numero_codigo_postal":"41640"},"empresa":{"id_empresa":"39","nombre_empresa":"COOPERATIVA"},"combustibles":[{"id_carburante":"8","tipo_carburante":"gasóleo B","precio_carburante":0.99,"fecha_act_precio_carburante":"15/11/24 20:00"}]}