{"id_estacion":"3852","tipo_estacion":"Terrestre","margen_estacion":"D","horario_estacion":"L-D: 06:00-00:00","direccion_estacion":"CARRETERA CM-4127 KM. 2,350","latitud_estacion":38.970417,"longitud_estacion":-3.902361,"ubicacion":{"id_localidad":"1318","nombre_localidad":"MIGUELTURRA","id_municipio":"1043","nombre_municipio":"MIGUELTURRA","id_provincia":"17","nombre_provincia":"CIUDAD REAL","id_codigo_postal":"1455","numero_codigo_postal":"13170"},"empresa":{"id_empresa":"6","nombre_empresa":"CEPSA"},"combustibles":[{"id_carburante":"7","tipo_carburante":"gasóleo Premium","precio_carburante":1.519,"fecha_act_precio_carburante":"11/11/24 19:46"}]}