{"id_estacion":"10659","tipo_estacion":"Terrestre","margen_estacion":"N","horario_estacion":"L-D: 24H","direccion_estacion":"CAMINO DE LA DEHESA, S/N.","latitud_estacion":39.68875,"longitud_estacion":-4.156083,"ubicacion":{"id_localidad":"3795","nombre_localidad":"PULGAR","id_municipio":"3013","nombre_municipio":"PULGAR","id_provincia":"48","nombre_provincia":"TOLEDO","id_codigo_postal":"4194","numero_codigo_postal":"45125"},"empresa":{"id_empresa":"3589","nombre_empresa":"COOP. SAN ANTON"},"combustibles":[{"id_carburante":"8","tipo_carburante":"gasóleo B","precio_carburante":0.905,"fecha_act_precio_carburante":"11/11/24 14:42"}]}