{"id_estacion":"2379","tipo_estacion":"Terrestre","margen_estacion":"D","horario_estacion":"L-D: 24H","direccion_estacion":"CALLE MEXICO, S/N","latitud_estacion":41.443167,"longitud_estacion":1.981333,"ubicacion":{"id_localidad":"757","nombre_localidad":"SANT ANDREU DE LA BARCA","id_municipio":"579","nombre_municipio":"SANT ANDREU DE LA BARCA","id_provincia":"9","nombre_provincia":"BARCELONA","id_codigo_postal":"878","numero_codigo_postal":"08740"},"empresa":{"id_empresa":"686","nombre_empresa":"PETROCAT DIRECTE"},"combustibles":[{"id_carburante":"7","tipo_carburante":"gasóleo Premium","precio_carburante":1.509,"fecha_act_precio_carburante":"16/11/24 0:00"}]}